wgctl.py
wgctl-0.6.1.dist-info/licenses/LICENSE
wgctl-0.6.1.dist-info/METADATA
wgctl-0.6.1.dist-info/WHEEL
wgctl-0.6.1.dist-info/entry_points.txt
wgctl-0.6.1.dist-info/top_level.txt
wgctl-0.6.1.dist-info/RECORD
